aim/VERSION
aim/__about__.py
aim/__init__.py
aim/__version__.py
aim/hugging_face.py
aim/keras.py
aim/pytorch_lightning.py
aim/tensorflow.py
aim/xgboost.py
aim/artifacts/__init__.py
aim/artifacts/artifact.py
aim/artifacts/artifact_writer.py
aim/artifacts/map.py
aim/artifacts/metric.py
aim/artifacts/model.py
aim/artifacts/record.py
aim/artifacts/record_writer.py
aim/artifacts/utils.py
aim/artifacts/proto/__init__.py
aim/artifacts/proto/base_pb2.py
aim/artifacts/proto/metric_pb2.py
aim/cli/__init__.py
aim/cli/cli.py
aim/cli/configs.py
aim/cli/experiment/__init__.py
aim/cli/experiment/commands.py
aim/cli/init/__init__.py
aim/cli/init/commands.py
aim/cli/status/__init__.py
aim/cli/status/commands.py
aim/cli/up/__init__.py
aim/cli/up/commands.py
aim/cli/up/utils.py
aim/cli/version/__init__.py
aim/cli/version/commands.py
aim/engine/__init__.py
aim/engine/configs.py
aim/engine/types.py
aim/engine/utils.py
aim/engine/profile/__init__.py
aim/engine/profile/profile.py
aim/engine/repo/__init__.py
aim/engine/repo/metric.py
aim/engine/repo/repo.py
aim/engine/repo/run.py
aim/engine/repo/trace.py
aim/engine/repo/utils.py
aim/engine/repo/dql/__init__.py
aim/engine/repo/dql/select.py
aim/ql/__init__.py
aim/ql/utils.py
aim/ql/grammar/__init__.py
aim/ql/grammar/atom.py
aim/ql/grammar/expression.py
aim/ql/grammar/statement.py
aim/ql/tokens/__init__.py
aim/ql/tokens/token.py
aim/ql/tokens/types.py
aim/ql/tree/__init__.py
aim/ql/tree/abstract_syntax_tree.py
aim/ql/tree/base.py
aim/ql/tree/binary_expression_tree.py
aim/ql/tree/node.py
aim/resource/__init__.py
aim/resource/stat.py
aim/resource/tracker.py
aim/resource/utils.py
aim/sdk/__init__.py
aim/sdk/flush.py
aim/sdk/init.py
aim/sdk/select.py
aim/sdk/track.py
aim/sdk/utils.py
aim/sdk/adapters/__init__.py
aim/sdk/adapters/hugging_face.py
aim/sdk/adapters/keras.py
aim/sdk/adapters/keras_mixins.py
aim/sdk/adapters/pytorch_lightning.py
aim/sdk/adapters/tensorflow.py
aim/sdk/adapters/xgboost.py
aim/sdk/session/__init__.py
aim_cli-2.7.4.dist-info/LICENSE
aim_cli-2.7.4.dist-info/METADATA
aim_cli-2.7.4.dist-info/WHEEL
aim_cli-2.7.4.dist-info/entry_points.txt
aim_cli-2.7.4.dist-info/top_level.txt
aim_cli-2.7.4.dist-info/RECORD
